odoo/addons/__init__.py
odoo/addons/website_forum/__init__.py
odoo/addons/website_forum/__manifest__.py
odoo/addons/website_forum/controllers/__init__.py
odoo/addons/website_forum/controllers/main.py
odoo/addons/website_forum/data/badges_answer.xml
odoo/addons/website_forum/data/badges_moderation.xml
odoo/addons/website_forum/data/badges_participation.xml
odoo/addons/website_forum/data/badges_question.xml
odoo/addons/website_forum/data/forum_data.xml
odoo/addons/website_forum/data/forum_default_faq.html
odoo/addons/website_forum/data/forum_demo.xml
odoo/addons/website_forum/i18n/af.po
odoo/addons/website_forum/i18n/am.po
odoo/addons/website_forum/i18n/ar.po
odoo/addons/website_forum/i18n/bg.po
odoo/addons/website_forum/i18n/bs.po
odoo/addons/website_forum/i18n/ca.po
odoo/addons/website_forum/i18n/cs.po
odoo/addons/website_forum/i18n/da.po
odoo/addons/website_forum/i18n/de.po
odoo/addons/website_forum/i18n/el.po
odoo/addons/website_forum/i18n/en_GB.po
odoo/addons/website_forum/i18n/es.po
odoo/addons/website_forum/i18n/es_CO.po
odoo/addons/website_forum/i18n/es_DO.po
odoo/addons/website_forum/i18n/es_EC.po
odoo/addons/website_forum/i18n/es_PE.po
odoo/addons/website_forum/i18n/et.po
odoo/addons/website_forum/i18n/eu.po
odoo/addons/website_forum/i18n/fa.po
odoo/addons/website_forum/i18n/fi.po
odoo/addons/website_forum/i18n/fo.po
odoo/addons/website_forum/i18n/fr.po
odoo/addons/website_forum/i18n/gl.po
odoo/addons/website_forum/i18n/gu.po
odoo/addons/website_forum/i18n/he.po
odoo/addons/website_forum/i18n/hr.po
odoo/addons/website_forum/i18n/hu.po
odoo/addons/website_forum/i18n/id.po
odoo/addons/website_forum/i18n/is.po
odoo/addons/website_forum/i18n/it.po
odoo/addons/website_forum/i18n/ja.po
odoo/addons/website_forum/i18n/ka.po
odoo/addons/website_forum/i18n/kab.po
odoo/addons/website_forum/i18n/ko.po
odoo/addons/website_forum/i18n/lo.po
odoo/addons/website_forum/i18n/lt.po
odoo/addons/website_forum/i18n/lv.po
odoo/addons/website_forum/i18n/mk.po
odooku_odoo_website_forum-11.0.7.dist-info/LICENSE
odooku_odoo_website_forum-11.0.7.dist-info/METADATA
odooku_odoo_website_forum-11.0.7.dist-info/WHEEL
odooku_odoo_website_forum-11.0.7.dist-info/top_level.txt
odooku_odoo_website_forum-11.0.7.dist-info/RECORD
